adorn/__init__.py
adorn/alter/__init__.py
adorn/alter/alter.py
adorn/alter/dict_alter.py
adorn/data/__init__.py
adorn/data/constructor.py
adorn/data/parameter.py
adorn/exception/__init__.py
adorn/exception/configuration_error.py
adorn/exception/type_check_error.py
adorn/orchestrator/__init__.py
adorn/orchestrator/base.py
adorn/orchestrator/orchestrator.py
adorn/params.py
adorn/py.typed
adorn/unit/__init__.py
adorn/unit/anum.py
adorn/unit/complex.py
adorn/unit/constructor_value.py
adorn/unit/dataclass.py
adorn/unit/parameter_value.py
adorn/unit/python.py
adorn/unit/search/__init__.py
adorn/unit/search/grid.py
adorn/unit/search/search.py
adorn/unit/simple.py
adorn/unit/template.py
adorn/unit/unit.py
adorn/unit/value.py
adorn-0.1.7.dist-info/LICENSE.rst
adorn-0.1.7.dist-info/METADATA
adorn-0.1.7.dist-info/WHEEL
adorn-0.1.7.dist-info/RECORD
