Metadata-Version: 2.1
Name: adorn
Version: 0.1.7
Summary: Adorn
Home-page: https://github.com/pyadorn/adorn
License: Apache-2.0
Author: Jacob Baumbach
Author-email: jacob.baumbach@hey.com
Requires-Python: >=3.10.0,<4.0.0
Classifier: Development Status :: 1 - Planning
Classifier: License :: OSI Approved :: Apache Software License
Classifier: Programming Language :: Python :: 3
Classifier: Programming Language :: Python :: 3.10
Classifier: Programming Language :: Python :: 3.11
Classifier: Programming Language :: Python :: 3.12
Requires-Dist: pyyaml (>=6.0.0,<7.0.0)
Requires-Dist: tomli (>=2.0.1,<3.0.0)
Project-URL: Changelog, https://github.com/pyadorn/adorn/releases
Project-URL: Documentation, https://pyadorn.github.io/adorn/
Project-URL: Repository, https://github.com/pyadorn/adorn
